{
    "id": "level_01",
    "name": "First Breath",
    "pack": "FREE",
    "description": "A barren rocky planet with a thin CO2 atmosphere, frozen oceans, and a weak magnetic field. Establish stable microbial life for 10 million years.",
    "starting_seed": 7749,
    "starting_params": {
        "gravity": 9.2,
        "rotation_rate": 1.1,
        "axial_tilt": 18.0,
        "core_heat": 0.2,
        "magnetic_field": 0.2,
        "atmosphere": {
            "pressure": 0.4,
            "o2": 0.01,
            "co2": 0.15,
            "toxicity": 0.1
        },
        "hydrology": {
            "ocean_coverage": 0.3,
            "salinity": 0.04,
            "current_strength": 0.2,
            "ice_fraction": 0.6
        }
    },
    "allowed_interventions": ["AdjustCO2", "AdjustO2", "NutrientBloom", "IceMeltPulse"],
    "energy_budget": 50.0,
    "objective": {
        "type": "MicrobialStability",
        "min_biomass": 5000.0,
        "required_duration_steps": 10000000
    },
    "fail_conditions": ["Extinction"]
}
